thuongcli/__init__.py
thuongcli/detect_hand.py
thuongcli/isM_my_control_by_hand.py
thuongcli/my_assistant.py
thuongcli/thuongcli.py
thuongcli-1.0.9.dist-info/licenses/LICENSE
thuongcli-1.0.9.dist-info/METADATA
thuongcli-1.0.9.dist-info/WHEEL
thuongcli-1.0.9.dist-info/entry_points.txt
thuongcli-1.0.9.dist-info/top_level.txt
thuongcli-1.0.9.dist-info/RECORD
