Metadata-Version: 2.4
Name: thuongcli
Version: 1.0.9
Summary: Điều khiển máy tính bằng CLI
Home-page: https://github.com/qbquangb/thuongcli
Author: Tran Dinh Thuong
Author-email: qbquangbinh@gmail.com
Classifier: Programming Language :: Python :: 3
Classifier: Programming Language :: Python :: 3.7
Classifier: Programming Language :: Python :: 3.8
Classifier: Programming Language :: Python :: 3.9
Classifier: Operating System :: OS Independent
Requires-Python: >=3.7
License-File: LICENSE
Requires-Dist: thuonglib>=1.0.4
Dynamic: author
Dynamic: author-email
Dynamic: classifier
Dynamic: description
Dynamic: description-content-type
Dynamic: home-page
Dynamic: license-file
Dynamic: requires-dist
Dynamic: requires-python
Dynamic: summary
